mkdocs_include_folders/__init__.py
mkdocs_include_folders/plugin.py
mkdocs_include_folders-0.1.4.dist-info/LICENSE
mkdocs_include_folders-0.1.4.dist-info/METADATA
mkdocs_include_folders-0.1.4.dist-info/WHEEL
mkdocs_include_folders-0.1.4.dist-info/entry_points.txt
mkdocs_include_folders-0.1.4.dist-info/top_level.txt
mkdocs_include_folders-0.1.4.dist-info/RECORD
