Metadata-Version: 2.1
Name: mkdocs-include-folders
Version: 0.1.4
Summary: A mkdocs plugin that lets you include subfolder of a top level tree.
Home-page: https://github.com/hhdale/mkdocs-include-folders
Author: Håkon Haugholt-Dale
Author-email: hakon.dale@gmail.com
License: Apache
Platform: UNKNOWN
License-File: LICENSE
Requires-Dist: mkdocs
